{
  "main": {
    "id": "6065c48e72f12bd9",
    "type": "split",
    "children": [
      {
        "id": "c51cd3454ca80f91",
        "type": "tabs",
        "children": [
          {
            "id": "033ae7710fa94f2a",
            "type": "leaf",
            "state": {
              "type": "markdown",
              "state": {
                "file": "Pre-order vs. Purchase Order (PO).md",
                "mode": "source",
                "source": false
              },
              "icon": "lucide-file",
              "title": "Pre-order vs. Purchase Order (PO)"
            }
          },
          {
            "id": "64e67328f4944c74",
            "type": "leaf",
            "state": {
              "type": "canvas",
              "state": {
                "file": "BikeMeNow Architecture.canvas",
                "viewState": {
                  "x": 7471.812912397004,
                  "y": 3636.4999518103086,
                  "zoom": -0.9883303874455165
                }
              },
              "icon": "lucide-layout-dashboard",
              "title": "BikeMeNow Architecture"
            }
          }
        ],
        "currentTab": 1
      }
    ],
    "direction": "vertical"
  },
  "left": {
    "id": "6a10767784a3840a",
    "type": "split",
    "children": [
      {
        "id": "c1c730949d63554d",
        "type": "tabs",
        "children": [
          {
            "id": "39c85f4d022a95d5",
            "type": "leaf",
            "state": {
              "type": "file-explorer",
              "state": {
                "sortOrder": "alphabetical",
                "autoReveal": false
              },
              "icon": "lucide-folder-closed",
              "title": "Files"
            }
          },
          {
            "id": "c6abdb798673262d",
            "type": "leaf",
            "state": {
              "type": "search",
              "state": {
                "query": "",
                "matchingCase": false,
                "explainSearch": false,
                "collapseAll": false,
                "extraContext": false,
                "sortOrder": "alphabetical"
              },
              "icon": "lucide-search",
              "title": "Search"
            }
          },
          {
            "id": "c0528c47107d7244",
            "type": "leaf",
            "state": {
              "type": "bookmarks",
              "state": {},
              "icon": "lucide-bookmark",
              "title": "Bookmarks"
            }
          }
        ]
      }
    ],
    "direction": "horizontal",
    "width": 310.5
  },
  "right": {
    "id": "1b9318455e0410ab",
    "type": "split",
    "children": [
      {
        "id": "774dd718a233fae8",
        "type": "tabs",
        "children": [
          {
            "id": "4365db19349c4d15",
            "type": "leaf",
            "state": {
              "type": "backlink",
              "state": {
                "file": "AVA MC Notes.md",
                "collapseAll": false,
                "extraContext": false,
                "sortOrder": "alphabetical",
                "showSearch": false,
                "searchQuery": "",
                "backlinkCollapsed": false,
                "unlinkedCollapsed": true
              },
              "icon": "links-coming-in",
              "title": "Backlinks for AVA MC Notes"
            }
          },
          {
            "id": "36be22986a3cecb9",
            "type": "leaf",
            "state": {
              "type": "outgoing-link",
              "state": {
                "file": "AVA MC Notes.md",
                "linksCollapsed": false,
                "unlinkedCollapsed": true
              },
              "icon": "links-going-out",
              "title": "Outgoing links from AVA MC Notes"
            }
          },
          {
            "id": "9ac7fbb8868d1099",
            "type": "leaf",
            "state": {
              "type": "tag",
              "state": {
                "sortOrder": "frequency",
                "useHierarchy": true,
                "showSearch": false,
                "searchQuery": ""
              },
              "icon": "lucide-tags",
              "title": "Tags"
            }
          },
          {
            "id": "3c087466a90d9866",
            "type": "leaf",
            "state": {
              "type": "all-properties",
              "state": {
                "sortOrder": "frequency",
                "showSearch": false,
                "searchQuery": ""
              },
              "icon": "lucide-archive",
              "title": "All properties"
            }
          },
          {
            "id": "2a0548fc8dd2a3fd",
            "type": "leaf",
            "state": {
              "type": "outline",
              "state": {
                "file": "AVA MC Notes.md",
                "followCursor": false,
                "showSearch": false,
                "searchQuery": ""
              },
              "icon": "lucide-list",
              "title": "Outline of AVA MC Notes"
            }
          }
        ]
      }
    ],
    "direction": "horizontal",
    "width": 300,
    "collapsed": true
  },
  "left-ribbon": {
    "hiddenItems": {
      "switcher:Open quick switcher": false,
      "graph:Open graph view": false,
      "canvas:Create new canvas": false,
      "daily-notes:Open today's daily note": false,
      "templates:Insert template": false,
      "command-palette:Open command palette": false,
      "bases:Create new base": false
    }
  },
  "active": "64e67328f4944c74",
  "lastOpenFiles": [
    "Images/Pasted image 20260324114221.png",
    "BikeMeNow Architecture.canvas",
    "Images/Pasted image 20260326124440.png",
    "Images/Pasted image 20260326124354.png",
    "Images/Pasted image 20260326123644.png",
    "Images/Pasted image 20260326123640.png",
    "Images/Pasted image 20260326123106.png",
    "Images/Pasted image 20260326122906.png",
    "Images/Pasted image 20260326121620.png",
    "Images/Pasted image 20260326121206.png",
    "Images/Pasted image 20260326120947.png",
    "Images/Pasted image 20260326114220.png",
    "Pre-order vs. Purchase Order (PO).md",
    "Mindmaps/Motorcycle World Mindmap.canvas",
    "Mindmaps/DL Software Mindmap.canvas",
    "DLsoftware notes/Tax-living vs. Tax-Dead Motorcycles..md",
    "DLsoftware notes/DL Software AVA Interview notes.md",
    "Notes/AVA MC Seller Notes Final Draft.md",
    "Notes/AVA MC Seller Notes Thursday 12-2.md",
    "Notes/AVA MC Anteckningar 28-1.md",
    "Prototype Solutions.md",
    "Journey Maps & Core flows.canvas",
    "Prototype prompt notes.md",
    "Andrews Figma Design Structure.canvas",
    "System Requirements & Pain points.canvas",
    "Insurance, registration, warranty structure part 1.md",
    "Insurance Quotes, Policy terms and Pre-approved customer.md",
    "Anteckningar inför onsdag 25-2.md",
    "Notes/AVA MC Seller Notes 28-1.md",
    "Notes/AVA MC Seller Notes Thursday 15-1.md",
    "Insurance, registration, warranty structure part 2.md",
    "Notes/AVA MC Seller Notes Tuesday 13-1.md",
    "Notes/AVA MC Försäljningsanteckningar Tisdag 13-1.md",
    "Insurance, registration, warranty structure part 3 (Structured standard MC sales process).md",
    "Mindmaps/AVA MC Mindmap.canvas",
    "Mindmaps/AVA MC Notes.md",
    "Lennarts Vision for our software to the motorcycle industry.md",
    "Differences between Pre-orders & Purchase Orders Part 2.md",
    "Github Notes.md",
    "Differences between Pre-orders & Purchase Orders Part 1.md",
    "Invoice problems when there's no Purchase Order.md",
    "Mindmaps",
    "OEM systems & dealership DMS systems.md",
    "Purchase list vs. Purchase Order (PO).md",
    "Images",
    "DLsoftware notes",
    "Notes"
  ]
}